systemair/VERSION.py
systemair/__init__.py
systemair/saveconnect/__init__.py
systemair/saveconnect/auth.py
systemair/saveconnect/const.py
systemair/saveconnect/data.py
systemair/saveconnect/graphql.py
systemair/saveconnect/models.py
systemair/saveconnect/register.py
systemair/saveconnect/registry.py
systemair/saveconnect/systemair.py
systemair/saveconnect/websocket.py
python_systemair_saveconnect-3.0.0rc12.dist-info/LICENSE.txt
python_systemair_saveconnect-3.0.0rc12.dist-info/METADATA
python_systemair_saveconnect-3.0.0rc12.dist-info/WHEEL
python_systemair_saveconnect-3.0.0rc12.dist-info/top_level.txt
python_systemair_saveconnect-3.0.0rc12.dist-info/RECORD
