Metadata-Version: 2.1
Name: python-systemair-saveconnect
Version: 3.0.0rc12
Summary: A python interface for the SaveConnect API
License: MIT
Keywords: systemair,saveconnect,home-automation
Classifier: Programming Language :: Python :: 3
Requires-Python: >=3.7
License-File: LICENSE.txt
Requires-Dist: beautifulsoup4
Requires-Dist: httpx
Requires-Dist: pydantic
Requires-Dist: importlib-metadata
